cimpact/__init__.py
cimpact/main.py
cimpact/utils.py
cimpact/models/__init__.py
cimpact/models/base_model.py
cimpact/models/prophet_model.py
cimpact/models/pyro_model.py
cimpact/models/tensorflow_model.py
cimpact-1.0.6.dist-info/METADATA
cimpact-1.0.6.dist-info/WHEEL
cimpact-1.0.6.dist-info/licenses/LICENSE.txt
cimpact-1.0.6.dist-info/RECORD
