Metadata-Version: 2.4
Name: cimpact
Version: 1.0.6
Summary: CImpact helps identifying causal impact in timeseries data
Project-URL: Homepage, https://github.com/Sanofi-Public/CImpact
Author: sanofi
License: Non Commercial License Notice: 
License-File: LICENSE.txt
Keywords: causal,inference,timeseries
Classifier: License :: Other/Proprietary License
Classifier: Operating System :: OS Independent
Classifier: Programming Language :: Python :: 3
Classifier: Programming Language :: Python :: 3.7
Classifier: Programming Language :: Python :: 3.8
Classifier: Programming Language :: Python :: 3.9
Classifier: Programming Language :: Python :: 3.10
Classifier: Programming Language :: Python :: 3.11
Classifier: Programming Language :: Python :: 3.12
Requires-Python: <3.13,>=3.7
Requires-Dist: black
Requires-Dist: build
Requires-Dist: hatchling
Requires-Dist: jinja2
Requires-Dist: matplotlib>=3.3.2
Requires-Dist: numpy>=1.19.2
Requires-Dist: pandas>=1.1.5
Requires-Dist: prophet>=1.0
Requires-Dist: pyro-ppl>=1.6.0
Requires-Dist: pytest
Requires-Dist: pytest-cov
Requires-Dist: pyyaml
Requires-Dist: seaborn
Requires-Dist: tensorflow-probability[tf]<=0.24,>=0.18
Requires-Dist: tensorflow>=2.10
Requires-Dist: tf-keras
Requires-Dist: torch>=1.7.0
